matatupath.py
matatupath-0.3.0.dist-info/LICENSE
matatupath-0.3.0.dist-info/WHEEL
matatupath-0.3.0.dist-info/METADATA
matatupath-0.3.0.dist-info/RECORD
