Metadata-Version: 2.1
Name: matatupath
Version: 0.3.0
Summary: 
License: MIT
Author: shadmeoli
Author-email: shadcodes@gmail.com
Requires-Python: >=3.9.5,<4.0.0
Classifier: License :: OSI Approved :: MIT License
Classifier: Programming Language :: Python :: 3
Classifier: Programming Language :: Python :: 3.10
Classifier: Programming Language :: Python :: 3.11
Requires-Dist: openrouteservice (>=2.3.3,<3.0.0)
Requires-Dist: polyline (>=1.4.0,<2.0.0)
